chela/__init__.py
chela/__main__.py
chela/chela_error.py
chela/formula_handler.py
chela-1.0.5.dist-info/LICENSE
chela-1.0.5.dist-info/METADATA
chela-1.0.5.dist-info/WHEEL
chela-1.0.5.dist-info/entry_points.txt
chela-1.0.5.dist-info/top_level.txt
chela-1.0.5.dist-info/RECORD
