Metadata-Version: 2.1
Name: chela
Version: 1.0.5
Summary: Library for handling chemical formulas
Home-page: https://github.com/ClaudioPereti/chela
Author: Claudio Pereti
License: MIT
Platform: UNKNOWN
Classifier: License :: OSI Approved :: MIT License
Classifier: Programming Language :: Python :: 3
Classifier: Programming Language :: Python :: 3.6
Requires-Dist: numpy
Requires-Dist: pandas
